marshmallow/__init__.py
marshmallow/base.py
marshmallow/class_registry.py
marshmallow/decorators.py
marshmallow/error_store.py
marshmallow/exceptions.py
marshmallow/fields.py
marshmallow/orderedset.py
marshmallow/py.typed
marshmallow/schema.py
marshmallow/types.py
marshmallow/utils.py
marshmallow/validate.py
marshmallow/warnings.py
marshmallow-3.20.2.dist-info/LICENSE
marshmallow-3.20.2.dist-info/METADATA
marshmallow-3.20.2.dist-info/WHEEL
marshmallow-3.20.2.dist-info/top_level.txt
marshmallow-3.20.2.dist-info/RECORD
