Metadata-Version: 2.1
Name: marshmallow
Version: 3.20.2
Summary: A lightweight library for converting complex datatypes to and from native Python datatypes.
Home-page: https://github.com/marshmallow-code/marshmallow
Author: Steven Loria
Author-email: sloria1@gmail.com
License: MIT
Project-URL: Changelog, https://marshmallow.readthedocs.io/en/latest/changelog.html
Project-URL: Issues, https://github.com/marshmallow-code/marshmallow/issues
Project-URL: Funding, https://opencollective.com/marshmallow
Project-URL: Tidelift, https://tidelift.com/subscription/pkg/pypi-marshmallow?utm_source=pypi-marshmallow&utm_medium=pypi
Keywords: serialization,rest,json,api,marshal,marshalling,deserialization,validation,schema
Classifier: Development Status :: 5 - Production/Stable
Classifier: Intended Audience :: Developers
Classifier: License :: OSI Approved :: MIT License
Classifier: Programming Language :: Python :: 3
Classifier: Programming Language :: Python :: 3.8
Classifier: Programming Language :: Python :: 3.9
Classifier: Programming Language :: Python :: 3.10
Classifier: Programming Language :: Python :: 3.11
Classifier: Programming Language :: Python :: 3.12
Requires-Python: >=3.8
License-File: LICENSE
Requires-Dist: packaging>=17.0
Provides-Extra: tests
Requires-Dist: pytest; extra == "tests"
Requires-Dist: pytz; extra == "tests"
Requires-Dist: simplejson; extra == "tests"
Provides-Extra: lint
Requires-Dist: pre-commit<4.0,>=2.4; extra == "lint"
Provides-Extra: docs
Requires-Dist: sphinx==7.2.6; extra == "docs"
Requires-Dist: sphinx-issues==3.0.1; extra == "docs"
Requires-Dist: alabaster==0.7.15; extra == "docs"
Requires-Dist: sphinx-version-warning==1.1.2; extra == "docs"
Requires-Dist: autodocsumm==0.2.12; extra == "docs"
Provides-Extra: dev
Requires-Dist: pytest; extra == "dev"
Requires-Dist: pytz; extra == "dev"
Requires-Dist: simplejson; extra == "dev"
Requires-Dist: pre-commit<4.0,>=2.4; extra == "dev"
Requires-Dist: tox; extra == "dev"
